torchmasked/__init__.py
torchmasked/functional.py
torchmasked/nn.py
torchmasked-0.1.0.dist-info/LICENSE
torchmasked-0.1.0.dist-info/METADATA
torchmasked-0.1.0.dist-info/WHEEL
torchmasked-0.1.0.dist-info/top_level.txt
torchmasked-0.1.0.dist-info/RECORD
