Metadata-Version: 2.1
Name: torchmasked
Version: 0.1.0
Summary: Tensor operations with mask for PyTorch.
Home-page: https://github.com/Renovamen/torchmasked
Author: Xiaohan Zou
Author-email: renovamenzxh@gmail.com
License: MIT
Platform: UNKNOWN
Classifier: Intended Audience :: Science/Research
Classifier: Development Status :: 3 - Alpha
Classifier: License :: OSI Approved :: MIT License
Classifier: Programming Language :: Python :: 3
Classifier: Topic :: Scientific/Engineering :: Artificial Intelligence
Requires-Python: >=3.6
License-File: LICENSE
Requires-Dist: torch (>=1.4.0)
Requires-Dist: torchvision (>=0.5.0)
Provides-Extra: dev
Requires-Dist: numpy (>=1.14.0) ; extra == 'dev'
